simplestRPC/__init__.py
simplestRPC/connector.py
simplestRPC/marshaller.py
simplestRPC/srpc_client.py
simplestRPC/srpc_server.py
simplestRPC/auxiliar/__init__.py
simplestRPC/auxiliar/aux.py
simplestRPC-1.4.13.dist-info/LICENSE.txt
simplestRPC-1.4.13.dist-info/METADATA
simplestRPC-1.4.13.dist-info/WHEEL
simplestRPC-1.4.13.dist-info/top_level.txt
simplestRPC-1.4.13.dist-info/RECORD
