Metadata-Version: 2.1
Name: simplestRPC
Version: 1.4.13
Summary: The easiest, cleanest and simplest way to creating interactions via RPC (Remove Procedure Call)
Home-page: https://github.com/davincif/simplestRPC
Author: davincif
Author-email: LDaVinciF@gmail.com
License: UNKNOWN
Project-URL: Bug Reports, https://github.com/davincif/simplestRPC/issues
Project-URL: Source, https://github.com/davincif/simplestRPC/
Keywords: RPC api development
Platform: UNKNOWN
Classifier: Development Status :: 5 - Production/Stable
Classifier: Intended Audience :: Developers
Classifier: Topic :: Software Development :: Build Tools
Classifier: License :: OSI Approved :: zlib/libpng License
Classifier: Programming Language :: Python :: 3.4
Classifier: Programming Language :: Python :: 3.5
Classifier: Programming Language :: Python :: 3.6
Requires-Dist: varenv
